Metadata-Version: 1.0
Name: pointscatter
Version: 0.0.1
Summary: scatter points
Home-page: UNKNOWN
Author: Hirokazu Ishida
Author-email: h-ishida@jsk.imi.i.u-tokyo.ac.jp
License: MIT
Platform: UNKNOWN
